[
    {
        "arxiv": null,
        "authors": "Yolanda Gil, Kelly M. Cobourn, Ewa Deelman, Christopher Duffy, Rafael Ferreira da Silva, Armen R. Kemanian, Craig A. Knoblock, Vipin Kumar, S. D. Peckham, Lucas Carvalho, Yao-Yi Chang, Daniel Garijo, Ankush Khandelwal, Deborah Khider, Minh Pahm, Jay Pujara, Varun Ratnakar, Maria Stoica, Bình Dương Vũ",
        "doi": null,
        "file_name": "20250512000646.pdf",
        "file_path": "../Pruebas/SalidaRSEFCompleta/iemss2018-MINT/PDFs/20250512000646.pdf",
        "pdf_link": "https://dgarijo.com/papers/iemss2018-MINT.pdf",
        "publication_date": "2018-01-01",
        "title": "MINT: Model INTegration Through Knowledge-Powered Data and Process Composition"
    }
]